napr/__init__.py
napr/apps/__init__.py
napr/apps/coconut/__init__.py
napr/apps/coconut/terpene/__init__.py
napr/apps/coconut/terpene/_base.py
napr/apps/coconut/terpene/explore.py
napr/apps/coconut/terpene/preprocessing.py
napr/apps/coconut/terpene/tests/conftest.py
napr/apps/coconut/terpene/tests/test_base_terpene.py
napr/apps/coconut/terpene/tests/test_explore.py
napr/apps/coconut/terpene/tests/test_preprocessing.py
napr/data/__init__.py
napr/data/_base.py
napr/data/_load.py
napr/data/tests/test_base_data.py
napr/data/tests/test_load.py
napr/evaluation/__init__.py
napr/evaluation/classification.py
napr/evaluation/tests/test_classification.py
napr/hyperopt/__init__.py
napr/hyperopt/_base.py
napr/hyperopt/tests/test_base_hyperopt.py
napr/plotting/__init__.py
napr/plotting/_base.py
napr/plotting/ggplot_bw.mplstyle
napr/plotting/ggplot_classic.mplstyle
napr/plotting/tests/test_base_plotting.py
napr/utils/__init__.py
napr/utils/_stat.py
napr/utils/decorators.py
napr/utils/helpers.py
napr/utils/random.py
napr/utils/tests/test_decorators.py
napr/utils/tests/test_helpers.py
napr/utils/tests/test_random.py
napr/utils/tests/test_stat.py
napr-0.1.5.dist-info/LICENSE
napr-0.1.5.dist-info/WHEEL
napr-0.1.5.dist-info/METADATA
napr-0.1.5.dist-info/RECORD
